Metadata-Version: 2.4
Name: mseep-mcp-x
Version: 0.1.3
Summary: This is MCP to fetch Tweets using RAPID API Client
Author-email: mseep <support@skydeck.ai>
Requires-Python: >=3.11
Requires-Dist: httpx>=0.28.1
Requires-Dist: mcp[cli]>=1.4.1
